verbose_terminal/__init__.py
verbose_terminal/main.py
verbose_terminal/styles.py
verbose_terminal-1.0.1.dist-info/LICENSE
verbose_terminal-1.0.1.dist-info/METADATA
verbose_terminal-1.0.1.dist-info/WHEEL
verbose_terminal-1.0.1.dist-info/top_level.txt
verbose_terminal-1.0.1.dist-info/RECORD
