Metadata-Version: 2.1
Name: verbose-terminal
Version: 1.0.1
Summary: A Python library for displaying messages in the terminal with styles and logging support.
Home-page: https://github.com/wipodev/Verbose_Terminal
Author: Wipodev
Author-email: ajwipo@gmail.com
License: MIT
Project-URL: Documentation, https://github.com/wipodev/Verbose_Terminal/blob/main/README.md
Project-URL: Source, https://github.com/wipodev/Verbose_Terminal
Project-URL: Bug Tracker, https://github.com/wipodev/Verbose_Terminal/issues
Keywords: python,terminal,console,verbose,verbose terminal,verbose terminal,verbose terminal
Classifier: Programming Language :: Python :: 3
Classifier: License :: OSI Approved :: MIT License
Classifier: Operating System :: OS Independent
Requires-Python: >=3.10
License-File: LICENSE
